[
    {
        "task_goal": "Pick and place objects",
        "task_progress_metadata": [
            {
                "narration_text": "Picks the unsure",
                "start_frame": 99,
                "stop_frame": 120
            },
            {
                "narration_text": "Presses the unsure",
                "start_frame": 120,
                "stop_frame": 191
            },
            {
                "narration_text": "Places down the unsure",
                "start_frame": 191,
                "stop_frame": 260
            },
            {
                "narration_text": "Picks the frying pan",
                "start_frame": 260,
                "stop_frame": 275
            },
            {
                "narration_text": "Turns the frying pan",
                "start_frame": 275,
                "stop_frame": 305
            }
        ]
    },
    {
        "task_goal": "Prepare the frying pan",
        "task_progress_metadata": [
            {
                "narration_text": "Picks the frying pan",
                "start_frame": 260,
                "stop_frame": 275
            },
            {
                "narration_text": "Turns the frying pan",
                "start_frame": 275,
                "stop_frame": 305
            },
            {
                "narration_text": "Places back the frying pan on the cooker",
                "start_frame": 305,
                "stop_frame": 424
            },
            {
                "narration_text": "Picks an onion",
                "start_frame": 424,
                "stop_frame": 430
            },
            {
                "narration_text": "Picks a knife",
                "start_frame": 430,
                "stop_frame": 490
            }
        ]
    },
    {
        "task_goal": "Pick and peel onions with hands",
        "task_progress_metadata": [
            {
                "narration_text": "Picks an onion",
                "start_frame": 424,
                "stop_frame": 430
            },
            {
                "narration_text": "Picks a knife",
                "start_frame": 430,
                "stop_frame": 490
            },
            {
                "narration_text": "Trims the end of the onion",
                "start_frame": 490,
                "stop_frame": 819
            },
            {
                "narration_text": "Peels the onion with hand",
                "start_frame": 819,
                "stop_frame": 836
            },
            {
                "narration_text": "Puts the onion peels in the the polythene paper",
                "start_frame": 836,
                "stop_frame": 880
            },
            {
                "narration_text": "Peels the onion with hand",
                "start_frame": 880,
                "stop_frame": 925
            },
            {
                "narration_text": "Puts the onion peels in the the polythene paper",
                "start_frame": 925,
                "stop_frame": 969
            },
            {
                "narration_text": "Peels the onion with hand",
                "start_frame": 969,
                "stop_frame": 1100
            },
            {
                "narration_text": "Puts the onion peels in the the polythene paper",
                "start_frame": 1100,
                "stop_frame": 1162
            },
            {
                "narration_text": "Peels the onion with hand",
                "start_frame": 1162,
                "stop_frame": 1467
            },
            {
                "narration_text": "Puts the onion peels in the the polythene paper",
                "start_frame": 1467,
                "stop_frame": 1510
            },
            {
                "narration_text": "Peels the onion with hand",
                "start_frame": 1510,
                "stop_frame": 1658
            },
            {
                "narration_text": "Puts the onion peels in the the polythene paper",
                "start_frame": 1658,
                "stop_frame": 1700
            },
            {
                "narration_text": "Peels the onion with hand",
                "start_frame": 1700,
                "stop_frame": 2062
            },
            {
                "narration_text": "Puts on the lights",
                "start_frame": 2062,
                "stop_frame": 2253
            }
        ]
    },
    {
        "task_goal": "Turn on lights",
        "task_progress_metadata": [
            {
                "narration_text": "Peels the onion with hand",
                "start_frame": 1700,
                "stop_frame": 2062
            },
            {
                "narration_text": "Puts on the lights",
                "start_frame": 2062,
                "stop_frame": 2253
            },
            {
                "narration_text": "Puts the onion peels in the the polythene paper",
                "start_frame": 2253,
                "stop_frame": 2359
            }
        ]
    },
    {
        "task_goal": "Throw knobs in the polythene paper",
        "task_progress_metadata": [
            {
                "narration_text": "Removes the knobs in the onion",
                "start_frame": 11192,
                "stop_frame": 11520
            },
            {
                "narration_text": "Puts the onions knobs in the polythene paper",
                "start_frame": 11520,
                "stop_frame": 11620
            },
            {
                "narration_text": "Opens the kitchen cabinet",
                "start_frame": 11620,
                "stop_frame": 11694
            }
        ]
    },
    {
        "task_goal": "Add cooking oil in frying pan",
        "task_progress_metadata": [
            {
                "narration_text": "Puts the onions knobs in the polythene paper",
                "start_frame": 11520,
                "stop_frame": 11620
            },
            {
                "narration_text": "Opens the kitchen cabinet",
                "start_frame": 11620,
                "stop_frame": 11694
            },
            {
                "narration_text": "Moves around the kitchen",
                "start_frame": 11694,
                "stop_frame": 11759
            },
            {
                "narration_text": "Picks a bottle of cooking oil",
                "start_frame": 11759,
                "stop_frame": 11862
            },
            {
                "narration_text": "Puts the cooking oil in the frying pan",
                "start_frame": 11862,
                "stop_frame": 12036
            },
            {
                "narration_text": "Returns back a bottle of cooking oil",
                "start_frame": 12036,
                "stop_frame": 12159
            },
            {
                "narration_text": "Turns on the cooker",
                "start_frame": 12159,
                "stop_frame": 12256
            }
        ]
    },
    {
        "task_goal": "Turn on the cooker",
        "task_progress_metadata": [
            {
                "narration_text": "Returns back a bottle of cooking oil",
                "start_frame": 12036,
                "stop_frame": 12159
            },
            {
                "narration_text": "Turns on the cooker",
                "start_frame": 12159,
                "stop_frame": 12256
            },
            {
                "narration_text": "Picks a knife",
                "start_frame": 12256,
                "stop_frame": 12261
            },
            {
                "narration_text": "Wipes the knife with hand",
                "start_frame": 12261,
                "stop_frame": 12330
            }
        ]
    },
    {
        "task_goal": "Adjust cooker knob",
        "task_progress_metadata": [
            {
                "narration_text": "Adjusts cooker knob",
                "start_frame": 20517,
                "stop_frame": 20551
            },
            {
                "narration_text": "Slices the onions in basin",
                "start_frame": 20551,
                "stop_frame": 21113
            },
            {
                "narration_text": "Places the mandolin safety holder on countertop",
                "start_frame": 21113,
                "stop_frame": 21130
            },
            {
                "narration_text": "Picks remaining piece on the slicer",
                "start_frame": 21130,
                "stop_frame": 21167
            },
            {
                "narration_text": "Places piece on countertop",
                "start_frame": 21167,
                "stop_frame": 21189
            },
            {
                "narration_text": "Picks another piece from the slicer",
                "start_frame": 21189,
                "stop_frame": 21213
            },
            {
                "narration_text": "Places piece on countertop",
                "start_frame": 21213,
                "stop_frame": 21226
            },
            {
                "narration_text": "Shifts mandolin safety holder position on the countertop",
                "start_frame": 21226,
                "stop_frame": 21326
            }
        ]
    }
]