[
    {
        "task_goal": "Mix and prepare the doughnut dough.",
        "task_progress_metadata": [
            {
                "narration_text": "#C C mixes a doughnut dough.",
                "start_frame": 1,
                "stop_frame": 773
            },
            {
                "narration_text": "#C C touches the dough mix.",
                "start_frame": 773,
                "stop_frame": 1071
            },
            {
                "narration_text": "#C C feels the doughnut mix.",
                "start_frame": 1071,
                "stop_frame": 1188
            },
            {
                "narration_text": "#C C mixes the pancake mix.",
                "start_frame": 1188,
                "stop_frame": 1569
            },
            {
                "narration_text": "#C C sits down.",
                "start_frame": 1569,
                "stop_frame": 1604
            },
            {
                "narration_text": "#C C mixes the doughnut dough.",
                "start_frame": 1604,
                "stop_frame": 2599
            },
            {
                "narration_text": "#C C looks at the doughnuts on a table.",
                "start_frame": 2599,
                "stop_frame": 3121
            },
            {
                "narration_text": "#C C mixes the doughnut dough.",
                "start_frame": 3121,
                "stop_frame": 3659
            },
            {
                "narration_text": "#C C sits well.",
                "start_frame": 3659,
                "stop_frame": 3716
            },
            {
                "narration_text": "#C C continues to mix the dough.",
                "start_frame": 3716,
                "stop_frame": 4870
            },
            {
                "narration_text": "#C C looks around.",
                "start_frame": 4870,
                "stop_frame": 6394
            },
            {
                "narration_text": "#C C looks around.",
                "start_frame": 6394,
                "stop_frame": 6495
            },
            {
                "narration_text": "#C C mixes the dough.",
                "start_frame": 6495,
                "stop_frame": 6558
            },
            {
                "narration_text": "#C C feels the dough mix.",
                "start_frame": 6558,
                "stop_frame": 6831
            }
        ]
    },
    {
        "task_goal": "Mixing the initial doughnut dough.",
        "task_progress_metadata": [
            {
                "narration_text": "#C C mixes a doughnut dough.",
                "start_frame": 1,
                "stop_frame": 773
            },
            {
                "narration_text": "#C C touches the dough mix.",
                "start_frame": 773,
                "stop_frame": 1071
            }
        ]
    },
    {
        "task_goal": "Touch and feel the dough mix.",
        "task_progress_metadata": [
            {
                "narration_text": "#C C mixes a doughnut dough.",
                "start_frame": 1,
                "stop_frame": 773
            },
            {
                "narration_text": "#C C touches the dough mix.",
                "start_frame": 773,
                "stop_frame": 1071
            },
            {
                "narration_text": "#C C feels the doughnut mix.",
                "start_frame": 1071,
                "stop_frame": 1188
            },
            {
                "narration_text": "#C C mixes the pancake mix.",
                "start_frame": 1188,
                "stop_frame": 1569
            }
        ]
    },
    {
        "task_goal": "Mix the pancake mix as an intermediate step.",
        "task_progress_metadata": [
            {
                "narration_text": "#C C feels the doughnut mix.",
                "start_frame": 1071,
                "stop_frame": 1188
            },
            {
                "narration_text": "#C C mixes the pancake mix.",
                "start_frame": 1188,
                "stop_frame": 1569
            },
            {
                "narration_text": "#C C sits down.",
                "start_frame": 1569,
                "stop_frame": 1604
            }
        ]
    },
    {
        "task_goal": "Take a short rest.",
        "task_progress_metadata": [
            {
                "narration_text": "#C C mixes the pancake mix.",
                "start_frame": 1188,
                "stop_frame": 1569
            },
            {
                "narration_text": "#C C sits down.",
                "start_frame": 1569,
                "stop_frame": 1604
            },
            {
                "narration_text": "#C C mixes the doughnut dough.",
                "start_frame": 1604,
                "stop_frame": 2599
            }
        ]
    },
    {
        "task_goal": "Resume mixing the doughnut dough.",
        "task_progress_metadata": [
            {
                "narration_text": "#C C sits down.",
                "start_frame": 1569,
                "stop_frame": 1604
            },
            {
                "narration_text": "#C C mixes the doughnut dough.",
                "start_frame": 1604,
                "stop_frame": 2599
            },
            {
                "narration_text": "#C C looks at the doughnuts on a table.",
                "start_frame": 2599,
                "stop_frame": 3121
            }
        ]
    },
    {
        "task_goal": "Check the doughnuts on the table.",
        "task_progress_metadata": [
            {
                "narration_text": "#C C mixes the doughnut dough.",
                "start_frame": 1604,
                "stop_frame": 2599
            },
            {
                "narration_text": "#C C looks at the doughnuts on a table.",
                "start_frame": 2599,
                "stop_frame": 3121
            },
            {
                "narration_text": "#C C mixes the doughnut dough.",
                "start_frame": 3121,
                "stop_frame": 3659
            }
        ]
    },
    {
        "task_goal": "Continue mixing the doughnut dough.",
        "task_progress_metadata": [
            {
                "narration_text": "#C C looks at the doughnuts on a table.",
                "start_frame": 2599,
                "stop_frame": 3121
            },
            {
                "narration_text": "#C C mixes the doughnut dough.",
                "start_frame": 3121,
                "stop_frame": 3659
            },
            {
                "narration_text": "#C C sits well.",
                "start_frame": 3659,
                "stop_frame": 3716
            },
            {
                "narration_text": "#C C continues to mix the dough.",
                "start_frame": 3716,
                "stop_frame": 4870
            },
            {
                "narration_text": "#C C looks around.",
                "start_frame": 4870,
                "stop_frame": 6394
            }
        ]
    },
    {
        "task_goal": "Look around while waiting.",
        "task_progress_metadata": [
            {
                "narration_text": "#C C continues to mix the dough.",
                "start_frame": 3716,
                "stop_frame": 4870
            },
            {
                "narration_text": "#C C looks around.",
                "start_frame": 4870,
                "stop_frame": 6394
            },
            {
                "narration_text": "#C C looks around.",
                "start_frame": 6394,
                "stop_frame": 6495
            },
            {
                "narration_text": "#C C mixes the dough.",
                "start_frame": 6495,
                "stop_frame": 6558
            }
        ]
    },
    {
        "task_goal": "Continue to mix and feel the dough mix.",
        "task_progress_metadata": [
            {
                "narration_text": "#C C looks around.",
                "start_frame": 6394,
                "stop_frame": 6495
            },
            {
                "narration_text": "#C C mixes the dough.",
                "start_frame": 6495,
                "stop_frame": 6558
            },
            {
                "narration_text": "#C C feels the dough mix.",
                "start_frame": 6558,
                "stop_frame": 6831
            },
            {
                "narration_text": "#C C looks around.",
                "start_frame": 6831,
                "stop_frame": 8224
            },
            {
                "narration_text": "#C C looks on the doughnuts on the table.",
                "start_frame": 8224,
                "stop_frame": 10488
            }
        ]
    },
    {
        "task_goal": "Check doughnuts on table and mix the dough further.",
        "task_progress_metadata": [
            {
                "narration_text": "#C C looks around.",
                "start_frame": 6831,
                "stop_frame": 8224
            },
            {
                "narration_text": "#C C looks on the doughnuts on the table.",
                "start_frame": 8224,
                "stop_frame": 10488
            },
            {
                "narration_text": "#C C mixes a dough in a dish.",
                "start_frame": 10488,
                "stop_frame": 11639
            },
            {
                "narration_text": "#C C feels the dough mix.",
                "start_frame": 11639,
                "stop_frame": 11835
            },
            {
                "narration_text": "#C C continues to mix the dough mix.",
                "start_frame": 11835,
                "stop_frame": 12341
            },
            {
                "narration_text": "#C C touches the dough mix with the left hand finger.",
                "start_frame": 12341,
                "stop_frame": 12397
            }
        ]
    },
    {
        "task_goal": "Taste and adjust the dough mixture.",
        "task_progress_metadata": [
            {
                "narration_text": "#C C continues to mix the dough mix.",
                "start_frame": 11835,
                "stop_frame": 12341
            },
            {
                "narration_text": "#C C touches the dough mix with the left hand finger.",
                "start_frame": 12341,
                "stop_frame": 12397
            },
            {
                "narration_text": "#C C tastes the dough mix.",
                "start_frame": 12397,
                "stop_frame": 12443
            },
            {
                "narration_text": "#C C wipes the finger on a sack cloth.",
                "start_frame": 12443,
                "stop_frame": 12532
            },
            {
                "narration_text": "#C C rinses the left hand finger in a bowl with water.",
                "start_frame": 12532,
                "stop_frame": 12604
            },
            {
                "narration_text": "#C C wipes the left hand finger on her cloth.",
                "start_frame": 12604,
                "stop_frame": 12843
            }
        ]
    },
    {
        "task_goal": "Add and mix salt into the dough mixture.",
        "task_progress_metadata": [
            {
                "narration_text": "#C C rinses the left hand finger in a bowl with water.",
                "start_frame": 12532,
                "stop_frame": 12604
            },
            {
                "narration_text": "#C C wipes the left hand finger on her cloth.",
                "start_frame": 12604,
                "stop_frame": 12843
            },
            {
                "narration_text": "#C C scoops some salt in a salt dish.",
                "start_frame": 12843,
                "stop_frame": 12964
            },
            {
                "narration_text": "#C C puts the salt in the dough mixture.",
                "start_frame": 12964,
                "stop_frame": 13004
            },
            {
                "narration_text": "#C C mix the dough mixture.",
                "start_frame": 13004,
                "stop_frame": 13597
            },
            {
                "narration_text": "#C C looks around the doughnuts on the table.",
                "start_frame": 13597,
                "stop_frame": 13760
            },
            {
                "narration_text": "#C C mixes the dough mixture.",
                "start_frame": 13760,
                "stop_frame": 14273
            }
        ]
    },
    {
        "task_goal": "Preparation with polythene bag.",
        "task_progress_metadata": [
            {
                "narration_text": "#C C looks around the doughnuts on the table.",
                "start_frame": 13597,
                "stop_frame": 13760
            },
            {
                "narration_text": "#C C mixes the dough mixture.",
                "start_frame": 13760,
                "stop_frame": 14273
            },
            {
                "narration_text": "#C C takes a polythene bag.",
                "start_frame": 14273,
                "stop_frame": 14309
            },
            {
                "narration_text": "#C C puts the polythene bag down.",
                "start_frame": 14309,
                "stop_frame": 14334
            },
            {
                "narration_text": "#C C mixes the dough mixture.",
                "start_frame": 14334,
                "stop_frame": 14700
            },
            {
                "narration_text": "#C C takes the polythene bag.",
                "start_frame": 14700,
                "stop_frame": 14746
            },
            {
                "narration_text": "#C C scoops some dough mixture.",
                "start_frame": 14746,
                "stop_frame": 14778
            },
            {
                "narration_text": "#C C puts the dough mixture in the polythene bag.",
                "start_frame": 14778,
                "stop_frame": 14871
            },
            {
                "narration_text": "#C C scoops dough mixture.",
                "start_frame": 14871,
                "stop_frame": 14893
            }
        ]
    },
    {
        "task_goal": "Put the dough mixture in a polythene bag and prepare saucepan.",
        "task_progress_metadata": [
            {
                "narration_text": "#C C puts the dough mixture in the polythene bag.",
                "start_frame": 14778,
                "stop_frame": 14871
            },
            {
                "narration_text": "#C C scoops dough mixture.",
                "start_frame": 14871,
                "stop_frame": 14893
            },
            {
                "narration_text": "#C C puts in the polythene bag.",
                "start_frame": 14893,
                "stop_frame": 14955
            },
            {
                "narration_text": "#C C turns a saucepan upright.",
                "start_frame": 14955,
                "stop_frame": 15008
            },
            {
                "narration_text": "#C C pushes the saucepan closer.",
                "start_frame": 15008,
                "stop_frame": 15109
            },
            {
                "narration_text": "#C C puts the dough mixture in the saucepan.",
                "start_frame": 15109,
                "stop_frame": 16271
            },
            {
                "narration_text": "#C C scoops more dough mixture.",
                "start_frame": 16271,
                "stop_frame": 16386
            },
            {
                "narration_text": "#C C takes the bowl with water.",
                "start_frame": 16386,
                "stop_frame": 16421
            },
            {
                "narration_text": "#C C pours the water in the dish.",
                "start_frame": 16421,
                "stop_frame": 16449
            },
            {
                "narration_text": "#C C puts the bowl with water down.",
                "start_frame": 16449,
                "stop_frame": 16502
            }
        ]
    },
    {
        "task_goal": "Rinse and clean the containers.",
        "task_progress_metadata": [
            {
                "narration_text": "#C C pours the water in the dish.",
                "start_frame": 16421,
                "stop_frame": 16449
            },
            {
                "narration_text": "#C C puts the bowl with water down.",
                "start_frame": 16449,
                "stop_frame": 16502
            },
            {
                "narration_text": "#C C rinses the dish.",
                "start_frame": 16502,
                "stop_frame": 16580
            },
            {
                "narration_text": "#C C pours water in the bowl.",
                "start_frame": 16580,
                "stop_frame": 16688
            },
            {
                "narration_text": "#C C puts the dish upside down on the sack cloth.",
                "start_frame": 16688,
                "stop_frame": 16734
            },
            {
                "narration_text": "#C C takes a salt dish.",
                "start_frame": 16734,
                "stop_frame": 16752
            },
            {
                "narration_text": "#C C puts the salt dish down.",
                "start_frame": 16752,
                "stop_frame": 16828
            },
            {
                "narration_text": "#C C takes a serving spoon from the bowl.",
                "start_frame": 16828,
                "stop_frame": 16874
            },
            {
                "narration_text": "#C C brings closer the dough mixture in the saucepan.",
                "start_frame": 16874,
                "stop_frame": 16949
            }
        ]
    },
    {
        "task_goal": "Final adjustments to the dough mixture in the saucepan.",
        "task_progress_metadata": [
            {
                "narration_text": "#C C takes a serving spoon from the bowl.",
                "start_frame": 16828,
                "stop_frame": 16874
            },
            {
                "narration_text": "#C C brings closer the dough mixture in the saucepan.",
                "start_frame": 16874,
                "stop_frame": 16949
            },
            {
                "narration_text": "#C C wipes the dough mixture from hands with the serving spoon.",
                "start_frame": 16949,
                "stop_frame": 17140
            },
            {
                "narration_text": "#C C puts the dough mixture from the spoon in the saucepan.",
                "start_frame": 17140,
                "stop_frame": 17236
            },
            {
                "narration_text": "#C C wipes more dough mixture from hands using the serving spoon.",
                "start_frame": 17236,
                "stop_frame": 17872
            },
            {
                "narration_text": "#C C puts the serving spoon in the saucepan.",
                "start_frame": 17872,
                "stop_frame": 17892
            },
            {
                "narration_text": "#C C pushes the saucepan.",
                "start_frame": 17892,
                "stop_frame": 17912
            },
            {
                "narration_text": "#C C takes a polythene bag with a dough mixture.",
                "start_frame": 17912,
                "stop_frame": 18031
            }
        ]
    },
    {
        "task_goal": "Closing and squeezing dough mixture in the polythene bag.",
        "task_progress_metadata": [
            {
                "narration_text": "#C C pushes the saucepan.",
                "start_frame": 17892,
                "stop_frame": 17912
            },
            {
                "narration_text": "#C C takes a polythene bag with a dough mixture.",
                "start_frame": 17912,
                "stop_frame": 18031
            },
            {
                "narration_text": "#C C closes the polythene bag.",
                "start_frame": 18031,
                "stop_frame": 18145
            },
            {
                "narration_text": "#C C opens the bottom of the polythene bag.",
                "start_frame": 18145,
                "stop_frame": 18176
            },
            {
                "narration_text": "#C C squeezes the dough mixture from the polythene bag in the saucepan.",
                "start_frame": 18176,
                "stop_frame": 18223
            },
            {
                "narration_text": "#C C rinses the bottom of the polythene bag.",
                "start_frame": 18223,
                "stop_frame": 18257
            },
            {
                "narration_text": "#C C squeezes dough mixture in the saucepan.",
                "start_frame": 18257,
                "stop_frame": 18349
            },
            {
                "narration_text": "#C C moves around .",
                "start_frame": 18349,
                "stop_frame": 18485
            },
            {
                "narration_text": "#C C squeezes dough mixture in the doughnuts on a table.",
                "start_frame": 18485,
                "stop_frame": 19036
            },
            {
                "narration_text": "#C C closes tightly the polythene bag.",
                "start_frame": 19036,
                "stop_frame": 19106
            }
        ]
    },
    {
        "task_goal": "Continue squeezing dough mixture and adjust paste consistency.",
        "task_progress_metadata": [
            {
                "narration_text": "#C C removes lumps",
                "start_frame": 77711,
                "stop_frame": 77749
            },
            {
                "narration_text": "#C C mixes the paste",
                "start_frame": 77749,
                "stop_frame": 78047
            },
            {
                "narration_text": "#C C removes lumps",
                "start_frame": 78047,
                "stop_frame": 78725
            },
            {
                "narration_text": "#O Person A adjusts C's camera",
                "start_frame": 78725,
                "stop_frame": 78825
            }
        ]
    }
]